autoadmin/__init__.py
autoadmin/admin.py
autoadmin/apps.py
autoadmin/handlers.py
autoadmin/models.py
autoadmin/settings.py
autoadmin/management/__init__.py
autoadmin/management/commands/__init__.py
autoadmin/management/commands/createautoadmin.py
autoadmin/migrations/0001_initial.py
autoadmin/migrations/__init__.py
autoadmin/templates/autoadmin/base.html
autoadmin/templatetags/__init__.py
autoadmin/templatetags/autoadmin_tags.py
django_autoadmin-1.1.1.dist-info/DESCRIPTION.rst
django_autoadmin-1.1.1.dist-info/METADATA
django_autoadmin-1.1.1.dist-info/RECORD
django_autoadmin-1.1.1.dist-info/WHEEL
django_autoadmin-1.1.1.dist-info/metadata.json
django_autoadmin-1.1.1.dist-info/top_level.txt
