Metadata-Version: 2.0
Name: django-autoadmin
Version: 1.1.1
Summary: Automatic admin users for Django projects.
Home-page: https://github.com/rosarior/django-autoadmin
Author: Roberto Rosario
Author-email: roberto.rosario.gonzalez@gmail.com
License: The MIT License (MIT)
Requires-Dist: django-solo (>=1.1.0)
